{
  "gitSyncId": "67543a55fd51167a0308d7f8_f8e4e5c4-c886-4848-af94-17c42ca9b942",
  "id": "Admin_send_issue_automation",
  "pluginId": "restapi-plugin",
  "pluginType": "API",
  "unpublishedAction": {
    "actionConfiguration": {
      "autoGeneratedHeaders": [
        {
          "key": "content-type",
          "value": "application/json"
        }
      ],
      "body": "{{{\n\t\"notification_type\": this.params.notification_type,\n\t\"title\": this.params.title,\n\t\"body\": this.params.body,\n\t\"users\": this.params.users\n}}}",
      "bodyFormData": [],
      "encodeParamsToggle": true,
      "formData": {
        "apiContentType": "application/json"
      },
      "headers": [],
      "httpMethod": "POST",
      "httpVersion": "HTTP11",
      "paginationType": "NONE",
      "path": "/functions/v1/send-notifications",
      "pluginSpecifiedTemplates": [
        {
          "value": true
        }
      ],
      "queryParameters": [],
      "timeoutInMillisecond": 10000
    },
    "confirmBeforeExecute": false,
    "datasource": {
      "id": "Role-Based API",
      "isAutoGenerated": false,
      "name": "Role-Based API",
      "pluginId": "restapi-plugin"
    },
    "dynamicBindingPathList": [
      {
        "key": "headers[0].value"
      },
      {
        "key": "body"
      }
    ],
    "executeOnLoad": false,
    "name": "send_issue_automation",
    "pageId": "Admin",
    "userSetOnLoad": false
  }
}