{
  "gitSyncId": "674603f58ce42030fd49a9d1_d619c618-bf66-4a59-a307-ed8a079a092a",
  "id": "Content_utils.addNewQuestion",
  "pluginId": "js-plugin",
  "pluginType": "JS",
  "unpublishedAction": {
    "actionConfiguration": {
      "encodeParamsToggle": true,
      "isAsync": true,
      "jsArguments": [],
      "paginationType": "NONE",
      "timeoutInMillisecond": 10000
    },
    "collectionId": "Content_utils",
    "confirmBeforeExecute": false,
    "datasource": {
      "isAutoGenerated": false,
      "name": "UNUSED_DATASOURCE",
      "pluginId": "js-plugin"
    },
    "dynamicBindingPathList": [
      {
        "key": "body"
      }
    ],
    "executeOnLoad": false,
    "fullyQualifiedName": "utils.addNewQuestion",
    "name": "addNewQuestion",
    "pageId": "Content",
    "userSetOnLoad": false
  }
}